FirstQuestion/function.v
module my_function(out,a,b,c,d,not_a,not_b,not_c,not_d);
	output out;
	input a,b,c,d,not_a,not_b,not_c,not_d;
	
	wire wire1;
	wire wire2;
	wire wire3;
	wire wire4;
	wire wire5;
	wire wire6;
	wire wire7;
	wire wire8;
	wire wire9;
	wire wire10;

	supply1 pwr;
	supply0 gnd;
	
	pmos(wire1,pwr,not_a);
	pmos(wire2,wire1,not_d);
	pmos(out,wire2,not_c);

	pmos(wire3,pwr,not_a);
	pmos(wire4,wire3,b);
	pmos(out,wire4,not_c);

	pmos(wire5,pwr,a);
	pmos(wire6,wire5,c);
	pmos(out,wire6,d);

	pmos(wire7,pwr,not_b);
	pmos(out,wire7,d);

	nmos(out,wire8,not_a);
	nmos(out,wire8,not_d);
	nmos(out,wire8,not_c);

	nmos(wire8,wire9,not_a);
	nmos(wire8,wire9,b);
	nmos(wire8,wire9,not_c);

	nmos(wire9,wire10,a);
	nmos(wire9,wire10,c);
	nmos(wire9,wire10,d);

	nmos(wire10,gnd,not_b);
	nmos(wire10,gnd,d);

endmodule

FirstQuestion/my_function_testbench.v
module my_function_testbench();
	wire out;
	reg a,b,c,d,not_a,not_b,not_c,not_d;

	my_function my_f(out,a,b,c,d,not_a,not_b,not_c,not_d);
	
	initial begin
		$dumpfile("my_functiond.vcd");
		$dumpvars(0,my_function_testbench);

		a=0;b=0;c=0;d=0;not_a=1;not_b=1;not_c=1;not_d=1;
		#20;
	
		a=0;b=0;c=0;d=1;not_a=1;not_b=1;not_c=1;not_d=0;
		#20;

		a=0;b=0;c=1;d=0;not_a=1;not_b=1;not_c=0;not_d=1;
		#20;
	
		a=0;b=0;c=1;d=1;not_a=1;not_b=1;not_c=0;not_d=0;
		#20;


		a=0;b=1;c=0;d=0;not_a=1;not_b=0;not_c=1;not_d=1;
		#20;
	
		a=0;b=1;c=0;d=1;not_a=1;not_b=0;not_c=1;not_d=0;
		#20;

		a=0;b=1;c=1;d=0;not_a=1;not_b=0;not_c=0;not_d=1;
		#20;
	
		a=0;b=1;c=1;d=1;not_a=1;not_b=0;not_c=0;not_d=0;
		#20;
		
	

		a=1;b=0;c=0;d=0;not_a=0;not_b=1;not_c=1;not_d=1;
		#20;
	
		a=1;b=0;c=0;d=1;not_a=0;not_b=1;not_c=1;not_d=0;
		#20;

		a=1;b=0;c=1;d=0;not_a=0;not_b=1;not_c=0;not_d=1;
		#20;
	
		a=1;b=0;c=1;d=1;not_a=0;not_b=1;not_c=0;not_d=0;
		#20;


		a=1;b=1;c=0;d=0;not_a=0;not_b=0;not_c=1;not_d=1;
		#20;
	
		a=1;b=1;c=0;d=1;not_a=0;not_b=0;not_c=1;not_d=0;
		#20;

		a=1;b=1;c=1;d=0;not_a=0;not_b=0;not_c=0;not_d=1;
		#20;
	
		a=1;b=1;c=1;d=1;not_a=0;not_b=0;not_c=0;not_d=0;
		#20;
		
		

		


	
		
	end	
endmodule

FirstQuestion/my_functiond.vcd
$date
	Mon Jan 18 04:40:21 2021
$end
$version
	Icarus Verilog
$end
$timescale
	1s
$end
$scope module my_function_testbench $end
$var wire 1 ! out $end
$var reg 1 " a $end
$var reg 1 # b $end
$var reg 1 $ c $end
$var reg 1 % d $end
$var reg 1 & not_a $end
$var reg 1 ' not_b $end
$var reg 1 ( not_c $end
$var reg 1 ) not_d $end
$scope module my_f $end
$var wire 1 " a $end
$var wire 1 # b $end
$var wire 1 $ c $end
$var wire 1 % d $end
$var wire 1 * gnd $end
$var wire 1 & not_a $end
$var wire 1 ' not_b $end
$var wire 1 ( not_c $end
$var wire 1 ) not_d $end
$var wire 1 ! out $end
$var wire 1 + pwr $end
$var wire 1 , wire1 $end
$var wire 1 - wire10 $end
$var wire 1 . wire2 $end
$var wire 1 / wire3 $end
$var wire 1 0 wire4 $end
$var wire 1 1 wire5 $end
$var wire 1 2 wire6 $end
$var wire 1 3 wire7 $end
$var wire 1 4 wire8 $end
$var wire 1 5 wire9 $end
$upscope $end
$upscope $end
$enddefinitions $end
#0
$dumpvars
z5
z4
z3
12
11
z0
z/
z.
0-
z,
1+
0*
1)
1(
1'
1&
0%
0$
0#
0"
1!
$end
#20
z.
0)
0!
04
05
1%
#40
z.
1)
0(
0%
z2
1$
#60
z.
0)
1%
#80
z.
1)
1(
13
z-
0'
1!
z4
z5
0%
12
0$
z0
1#
#100
z.
0)
0!
04
05
0-
1%
#120
z.
1)
0(
1!
z4
z5
z-
0%
z2
1$
#140
z.
0)
0!
04
05
0-
1%
#160
1)
1(
z3
1'
z.
1,
1/
0&
0!
04
05
0-
0%
0$
10
0#
z2
z1
1"
#180
1.
0)
1%
#200
z.
1)
1!
z4
0(
0%
z2
1$
#220
1.
0)
1%
#240
z.
1)
1(
13
z5
z-
0'
0%
z2
0$
z0
z4
1#
#260
1.
0)
0!
04
05
0-
1%
#280
z.
1)
0(
1!
z4
z5
z-
0%
z2
1$
#300
1.
0)
1!
04
05
0-
1%
